torchtel/__init__.py
torchtel/instrument.py
torchtel/py.typed
torchtel/setup.py
torchtel-0.0.3.dist-info/licenses/LICENSE
torchtel-0.0.3.dist-info/METADATA
torchtel-0.0.3.dist-info/WHEEL
torchtel-0.0.3.dist-info/top_level.txt
torchtel-0.0.3.dist-info/RECORD
