Metadata-Version: 2.4
Name: torchtel
Version: 0.0.3
Summary: 	OpenTelemetry auto instrumentation for pytorch
Author-email: Lucca Bertoncini <luccab@meta.com>, Billy Campoli <bcampoli@meta.com>
License: MIT License
Project-URL: Homepage, https://github.com/facebookresearch/torchtel
Project-URL: Issues, https://github.com/facebookresearch/torchtel/issues
Requires-Python: >=3.10
License-File: LICENSE
Requires-Dist: torch
Requires-Dist: opentelemetry-api
Requires-Dist: opentelemetry-instrumentation>=0.56b0
Requires-Dist: clusterscope>=0.0.9
Requires-Dist: opentelemetry-exporter-otlp>=1.35.0
Requires-Dist: opentelemetry-sdk>=1.35.0
Provides-Extra: dev
Requires-Dist: flake8>=7.3.0; extra == "dev"
Requires-Dist: mypy>=1.16.1; extra == "dev"
Requires-Dist: pre-commit>=4.2.0; extra == "dev"
Requires-Dist: black; extra == "dev"
Requires-Dist: ufmt; extra == "dev"
Requires-Dist: usort; extra == "dev"
Requires-Dist: build>=1.2.2.post1; extra == "dev"
Requires-Dist: twine>=6.1.0; extra == "dev"
Requires-Dist: mypy>=1.17.0; extra == "dev"
Dynamic: license-file
